Workbook
Name aporte: APP!$C$25
Name patrimonio: APP!$C$28
Name qtd_anos: APP!$C$26
Name rendimento_carteira: APP!$C$20
Name salario: APP!$C$19
Name sugestao_investimento: APP!$C$21
Name taxa_mensal: APP!$C$27

Sheet APP
B18: Configurações
B19: Salário | C19: 2000
B20: Rendimento Carteira | C20: 0.006
B21: Sugestão de Investimento (30%) | C21: =C19*30% -> 600
B24: INVESTIMENTO MENSAL
B25: Quanto investir por mês? | C25: 500
B26: Por Quantos Anos? | C26: 5
B27: Taxa de Rendimento Mensal? | C27: 0.01079
B28: Patrimônio Acumulado? | C28: =FV(taxa_mensal,qtd_anos*12,aporte*-1) -> 41888.457
B29: Dividendos Mensais? | C29: =patrimonio*rendimento_carteira -> 251.33074
B31: Cenários | D31: Dividendo
B32: Quanto em 2 Anos? | C32: =FV($C$27,$A33*12,$C$25*-1) -> 13613.814 | D32: =C32*rendimento_carteira -> 81.682882
A33: 2 | B33: Quanto em 5 Anos? | C33: =FV($C$27,$A34*12,$C$25*-1) -> 41888.457 | D33: =C33*rendimento_carteira -> 251.33074
A34: 5 | B34: Quanto em 10 Anos? | C34: =FV($C$27,$A35*12,$C$25*-1) -> 121642.11 | D34: =C34*rendimento_carteira -> 729.85264
A35: 10 | B35: Quanto em 20 Anos? | C35: =FV($C$27,$A36*12,$C$25*-1) -> 562599.2 | D35: =C35*rendimento_carteira -> 3375.5952
A36: 20 | B36: Quanto em 30 Anos? | C36: =FV($C$27,$A37*12,$C$25*-1) -> 2161084.8 | D36: =C36*rendimento_carteira -> 12966.509
A37: 30
B38: PERFIL | C38: Agressivo
B39: VALOR A SER INVESTIDO POR MÊS | C39: =aporte -> 500
B41: TIPO DE FII | C41: Percentual Sugerigo | D41: Valor
B42: PAPEL | C42: =VLOOKUP($C$38&"-"&B42,Folha2!$A$3:$D$20,4,FALSE) -> 0.5 | D42: =C42*$C$39 -> 250
B43: TIJOLO | C43: =VLOOKUP($C$38&"-"&B43,Folha2!$A$4:$D$20,4,FALSE) -> 0.1 | D43: =C43*$C$39 -> 50
B44: HÍBRIDOS | C44: =VLOOKUP($C$38&"-"&B44,Folha2!$A$4:$D$20,4,FALSE) -> 0.05 | D44: =C44*$C$39 -> 25
B45: FOFs | C45: =VLOOKUP($C$38&"-"&B45,Folha2!$A$4:$D$20,4,FALSE) -> 0.05 | D45: =C45*$C$39 -> 25
B46: DESENVOLVIMENTO | C46: =VLOOKUP($C$38&"-"&B46,Folha2!$A$4:$D$20,4,FALSE) -> 0.2 | D46: =C46*$C$39 -> 100
B47: HOTELARIAS | C47: =VLOOKUP($C$38&"-"&B47,Folha2!$A$4:$D$20,4,FALSE) -> 0.1 | D47: =C47*$C$39 -> 50
D48: =SUM(D42:D47) -> 500

Sheet Folha2
A2: CHAVE | B2: PERFIL | C2: TIPO DE FII | D2: %
A3: =B3&"-"&C3 -> Conservador-PAPEL | B3: Conservador | C3: PAPEL | D3: 0.3
A4: =B4&"-"&C4 -> Conservador-TIJOLO | B4: Conservador | C4: TIJOLO | D4: 0.5
A5: =B5&"-"&C5 -> Conservador-HÍBRIDOS | B5: Conservador | C5: HÍBRIDOS | D5: 0.1
A6: =B6&"-"&C6 -> Conservador-FOFs | B6: Conservador | C6: FOFs | D6: 0.1
A7: =B7&"-"&C7 -> Conservador-DESENVOLVIMENTO | B7: Conservador | C7: DESENVOLVIMENTO | D7: 0
A8: =B8&"-"&C8 -> Conservador-HOTELARIAS | B8: Conservador | C8: HOTELARIAS | D8: 0
A9: =B9&"-"&C9 -> Moderado-PAPEL | B9: Moderado | C9: PAPEL | D9: 0.32
A10: =B10&"-"&C10 -> Moderado-TIJOLO | B10: Moderado | C10: TIJOLO | D10: 0.35
A11: =B11&"-"&C11 -> Moderado-HÍBRIDOS | B11: Moderado | C11: HÍBRIDOS | D11: 0.08
A12: =B12&"-"&C12 -> Moderado-FOFs | B12: Moderado | C12: FOFs | D12: 0.05
A13: =B13&"-"&C13 -> Moderado-DESENVOLVIMENTO | B13: Moderado | C13: DESENVOLVIMENTO | D13: 0.05
A14: =B14&"-"&C14 -> Moderado-HOTELARIAS | B14: Moderado | C14: HOTELARIAS | D14: 0.1
... A20: =B20&"-"&C20 -> Agressivo-HOTELARIAS | B20: Agressivo | C20: HOTELARIAS | D20: 0.1
